{
    "texts": {
        "title": "ALMA UOVA\u003cbr/\u003e\u003cspan class=\"text-3xl md:text-5xl text-slate-800\"\u003eEccellenza Veneta, Energia Quotidiana\u003c/span\u003e",
        "subtitle": "Ho iniziato facendo ricerca, raccogliendo tutti gli spot commerciali per le uova e simili, italiani e stranieri. I migliori concorrenti del settore hanno altri budget ma possiamo comunque estrarre le cose migliori dai loro e vedere come comunicano i Big del settore."
    },
    "media": {
        "storyMedia0": "",
        "storyMedia4": "",
        "compVideo1": "",
        "compVideo3": "",
        "storyMedia9": "",
        "compVideo5": "",
        "storyMedia3": "",
        "storyMedia1": "",
        "storyMedia2": "",
        "compVideo2": "",
        "storyMedia13": "",
        "storyMedia8": "",
        "storyMedia10": "",
        "storyMedia12": "",
        "storyMedia6": "",
        "compVideo4": "",
        "storyMedia7": "",
        "storyMedia5": "",
        "storyMedia11": ""
    }
}